romspline/__init__.py
romspline/__version__.py
romspline/build_spline.py
romspline/convergence.py
romspline/cross_validation.py
romspline/example.py
romspline/example_2019-11-22a.py
romspline/greedy.py
romspline/h5splinetotxt.py
romspline/helpers.py
romspline/random_seeds.py
romspline/regression.py
romspline/regressionData.h5
romspline-1.1.6.dist-info/LICENSE
romspline-1.1.6.dist-info/METADATA
romspline-1.1.6.dist-info/WHEEL
romspline-1.1.6.dist-info/top_level.txt
romspline-1.1.6.dist-info/RECORD
