Metadata-Version: 2.1
Name: romspline
Version: 1.1.6
Summary: A Python package for building reduced-order models to interpolate univariate data.
Home-page: https://github.com/crgalley/romspline/
Author: Chad Galley
Author-email: crgalley@tapir.caltech.edu
License: UNKNOWN
Keywords: reduced order model spline interpolation data compression reduction
Platform: UNKNOWN
Classifier: Intended Audience :: Science/Research
Classifier: Natural Language :: English
Classifier: Topic :: Scientific/Engineering
Classifier: License :: OSI Approved :: MIT License
Classifier: Programming Language :: Python
Classifier: Operating System :: OS Independent
Requires-Dist: numpy
Requires-Dist: scipy
Requires-Dist: h5py (>=2.7.0)
Requires-Dist: pathlib2 ; python_version < "3.4"
